BCI2kReader/BCI2kReader.py
BCI2kReader/FileReader.py
BCI2kReader/__init__.py
BCI2kReader-0.32.dev0.dist-info/LICENSE
BCI2kReader-0.32.dev0.dist-info/METADATA
BCI2kReader-0.32.dev0.dist-info/WHEEL
BCI2kReader-0.32.dev0.dist-info/top_level.txt
BCI2kReader-0.32.dev0.dist-info/RECORD
