Metadata-Version: 2.1
Name: BCI2kReader
Version: 0.32.dev0
Summary: UNKNOWN
Home-page: https://github.com/neurotechcenter/BCI2kReader
Author: Markus Adamek
Author-email: adamek@neurotechcenter.com
License: GNU 3
Platform: UNKNOWN
Classifier: Development Status :: 4 - Beta
Classifier: Programming Language :: Python :: 3
Classifier: Programming Language :: Python :: 2
Requires-Dist: numpy
